setup.py
pyzaif/__init__.py
pyzaif/pyzaif.py
pyzaif.egg-info/PKG-INFO
pyzaif.egg-info/SOURCES.txt
pyzaif.egg-info/dependency_links.txt
pyzaif.egg-info/requires.txt
pyzaif.egg-info/top_level.txt
test/test_pyzaif.py