Metadata-Version: 1.1
Name: pyzaif
Version: 0.1.1
Summary: Python wrapper for zaif's REST API
Home-page: https://github.com/makino18/pyzaif
Author: maki
Author-email: makino.aaa@gmail.com
License: UNKNOWN
Keywords: bitcoin,zaif
Platform: UNKNOWN
Classifier: Programming Language :: Python
Classifier: Programming Language :: Python :: 3
Classifier: Environment :: Web Environment
Classifier: Intended Audience :: Developers
Classifier: License :: OSI Approved :: MIT License
Classifier: Operating System :: OS Independent
Classifier: Topic :: Internet :: WWW/HTTP
Classifier: Topic :: Software Development :: Libraries :: Python Modules
